ibooks_highlight_exporter/__init__.py
ibooks_highlight_exporter/base.py
ibooks_highlight_exporter/epub.py
ibooks_highlight_exporter/exporter.py
ibooks_highlight_exporter/helpers.py
ibooks_highlight_exporter/main.py
ibooks_highlight_exporter/models.py
ibooks_highlight_exporter/Парк Крымского периода. Хроники третьего срока_highlights.html
ibooks_highlight_exporter-0.1.11.dist-info/entry_points.txt
ibooks_highlight_exporter-0.1.11.dist-info/LICENSE
ibooks_highlight_exporter-0.1.11.dist-info/WHEEL
ibooks_highlight_exporter-0.1.11.dist-info/METADATA
ibooks_highlight_exporter-0.1.11.dist-info/RECORD
