Metadata-Version: 2.1
Name: ibooks-highlight-exporter
Version: 0.1.11
Summary: Export highlights from your iBooks to HTML including chapter titles
Author: Olga Andreeva
Author-email: indmajor64@gmail.com
Classifier: Programming Language :: Python :: 2
Classifier: Programming Language :: Python :: 2.7
Classifier: Programming Language :: Python :: 3
Classifier: Programming Language :: Python :: 3.4
Classifier: Programming Language :: Python :: 3.5
Classifier: Programming Language :: Python :: 3.6
Classifier: Programming Language :: Python :: 3.7
Classifier: Programming Language :: Python :: 3.8
Classifier: Programming Language :: Python :: 3.9
Requires-Dist: Click (>=7.0,<8.0)
Requires-Dist: lxml (>=4.4,<5.0)
